biograder/Homework.py
biograder/Parser.py
biograder/__init__.py
biograder/bio462_hw1.py
biograder/bio462_hw2.py
biograder/bio462_hw3.py
biograder/bio462_hw4.py
biograder/bio462_hw5.py
biograder/bio462_hw6.py
biograder/exceptions.py
biograder/file_download.py
biograder/file_tools.py
biograder/main.py
biograder/version.py
biograder/data_bio462_hw1/index_urls.tsv
biograder/data_bio462_hw2/index_urls.tsv
biograder/data_bio462_hw3/index_urls.tsv
biograder/data_bio462_hw4/index_urls.tsv
biograder/data_bio462_hw5/index_urls.tsv
biograder/data_bio462_hw6/index_urls.tsv
biograder-0.5.1.dist-info/LICENSE.md
biograder-0.5.1.dist-info/METADATA
biograder-0.5.1.dist-info/WHEEL
biograder-0.5.1.dist-info/top_level.txt
biograder-0.5.1.dist-info/RECORD
