Metadata-Version: 2.1
Name: biograder
Version: 0.5.1
Summary: Python packaging for biograder: automatic homework grading and hints
Home-page: https://github.com/PayneLab/biograder
Author: PayneLab
Author-email: sam_payne@byu.edu
License: UNKNOWN
Project-URL: Documentation, https://paynelab.github.io/biograder/
Platform: UNKNOWN
Classifier: Programming Language :: Python :: 3
Classifier: License :: OSI Approved :: MIT License
Classifier: Operating System :: OS Independent
Requires-Python: >=3.6.*
